[
  { "id": 1, "name": "智能手机", "region": "华东", "year": 2023, "count": 45 },
  { "id": 2, "name": "笔记本电脑", "region": "华北", "year": 2022, "count": 32 },
  { "id": 3, "name": "平板电脑", "region": "华南", "year": 2023, "count": 28 },
  { "id": 4, "name": "智能手表", "region": "华东", "year": 2024, "count": 67 },
  { "id": 5, "name": "蓝牙耳机", "region": "华北", "year": 2023, "count": 89 },
  { "id": 6, "name": "台式电脑", "region": "西南", "year": 2021, "count": 12 },
  { "id": 7, "name": "显示器", "region": "华东", "year": 2022, "count": 23 },
  { "id": 8, "name": "键盘", "region": "华南", "year": 2024, "count": 56 },
  { "id": 9, "name": "鼠标", "region": "华北", "year": 2023, "count": 78 },
  { "id": 10, "name": "路由器", "region": "华东", "year": 2022, "count": 34 },
  { "id": 11, "name": "智能音箱", "region": "华南", "year": 2023, "count": 45 },
  { "id": 12, "name": "相机", "region": "华北", "year": 2021, "count": 15 },
  { "id": 13, "name": "无人机", "region": "华东", "year": 2024, "count": 23 },
  { "id": 14, "name": "游戏机", "region": "西南", "year": 2023, "count": 34 },
  { "id": 15, "name": "智能眼镜", "region": "华南", "year": 2022, "count": 12 },
  { "id": 16, "name": "移动硬盘", "region": "华东", "year": 2023, "count": 45 },
  { "id": 17, "name": "U盘", "region": "华北", "year": 2024, "count": 67 },
  { "id": 18, "name": "充电宝", "region": "华南", "year": 2023, "count": 89 },
  { "id": 19, "name": "数据线", "region": "华东", "year": 2022, "count": 123 },
  { "id": 20, "name": "充电器", "region": "华北", "year": 2023, "count": 98 },
  { "id": 21, "name": "手机壳", "region": "西南", "year": 2024, "count": 156 },
  { "id": 22, "name": "贴膜", "region": "华东", "year": 2023, "count": 234 },
  { "id": 23, "name": "支架", "region": "华南", "year": 2022, "count": 45 },
  { "id": 24, "name": "散热器", "region": "华北", "year": 2023, "count": 34 },
  { "id": 25, "name": "扩展坞", "region": "华东", "year": 2024, "count": 23 },
  { "id": 26, "name": "网卡", "region": "华南", "year": 2021, "count": 12 },
  { "id": 27, "name": "声卡", "region": "华北", "year": 2022, "count": 8 },
  { "id": 28, "name": "麦克风", "region": "华东", "year": 2023, "count": 19 },
  { "id": 29, "name": "耳机", "region": "西南", "year": 2024, "count": 67 },
  { "id": 30, "name": "音响", "region": "华南", "year": 2023, "count": 45 },
  { "id": 31, "name": "投影仪", "region": "华东", "year": 2022, "count": 11 },
  { "id": 32, "name": "打印机", "region": "华北", "year": 2023, "count": 9 },
  { "id": 33, "name": "扫描仪", "region": "华南", "year": 2021, "count": 5 },
  { "id": 34, "name": "服务器", "region": "华东", "year": 2024, "count": 7 },
  { "id": 35, "name": "交换机", "region": "华北", "year": 2023, "count": 13 },
  { "id": 36, "name": "路由器", "region": "西南", "year": 2022, "count": 24 },
  { "id": 37, "name": "光猫", "region": "华东", "year": 2023, "count": 31 },
  { "id": 38, "name": "智能门锁", "region": "华南", "year": 2024, "count": 42 },
  { "id": 39, "name": "摄像头", "region": "华北", "year": 2023, "count": 53 },
  { "id": 40, "name": "传感器", "region": "华东", "year": 2022, "count": 64 },
  { "id": 41, "name": "智能灯泡", "region": "华南", "year": 2023, "count": 75 },
  { "id": 42, "name": "插座", "region": "华北", "year": 2024, "count": 86 },
  { "id": 43, "name": "开关", "region": "华东", "year": 2023, "count": 97 },
  { "id": 44, "name": "窗帘电机", "region": "西南", "year": 2022, "count": 108 },
  { "id": 45, "name": "扫地机", "region": "华南", "year": 2023, "count": 119 },
  { "id": 46, "name": "空气净化器", "region": "华东", "year": 2024, "count": 131 },
  { "id": 47, "name": "加湿器", "region": "华北", "year": 2023, "count": 142 },
  { "id": 48, "name": "除湿机", "region": "华南", "year": 2022, "count": 153 },
  { "id": 49, "name": "电风扇", "region": "华东", "year": 2023, "count": 164 },
  { "id": 50, "name": "取暖器", "region": "华北", "year": 2021, "count": 175 },
  { "id": 51, "name": "空调", "region": "西南", "year": 2024, "count": 186 },
  { "id": 52, "name": "冰箱", "region": "华东", "year": 2023, "count": 197 },
  { "id": 53, "name": "洗衣机", "region": "华南", "year": 2022, "count": 208 },
  { "id": 54, "name": "电视", "region": "华北", "year": 2023, "count": 219 },
  { "id": 55, "name": "微波炉", "region": "华东", "year": 2024, "count": 231 },
  { "id": 56, "name": "烤箱", "region": "华南", "year": 2023, "count": 242 },
  { "id": 57, "name": "电饭煲", "region": "华北", "year": 2022, "count": 253 },
  { "id": 58, "name": "破壁机", "region": "华东", "year": 2023, "count": 264 },
  { "id": 59, "name": "咖啡机", "region": "西南", "year": 2021, "count": 275 },
  { "id": 60, "name": "净水器", "region": "华南", "year": 2024, "count": 286 },
  { "id": 61, "name": "饮水机", "region": "华东", "year": 2023, "count": 297 },
  { "id": 62, "name": "吸尘器", "region": "华北", "year": 2022, "count": 308 },
  { "id": 63, "name": "洗地机", "region": "华南", "year": 2023, "count": 319 },
  { "id": 64, "name": "智能床垫", "region": "华东", "year": 2024, "count": 331 },
  { "id": 65, "name": "按摩椅", "region": "华北", "year": 2023, "count": 342 },
  { "id": 66, "name": "跑步机", "region": "西南", "year": 2022, "count": 353 },
  { "id": 67, "name": "动感单车", "region": "华东", "year": 2023, "count": 364 },
  { "id": 68, "name": "哑铃", "region": "华南", "year": 2021, "count": 375 },
  { "id": 69, "name": "瑜伽垫", "region": "华北", "year": 2024, "count": 386 },
  { "id": 70, "name": "健身车", "region": "华东", "year": 2023, "count": 397 },
  { "id": 71, "name": "智能手环", "region": "华南", "year": 2022, "count": 408 },
  { "id": 72, "name": "体脂秤", "region": "华北", "year": 2023, "count": 419 },
  { "id": 73, "name": "血压计", "region": "华东", "year": 2024, "count": 431 },
  { "id": 74, "name": "血糖仪", "region": "西南", "year": 2023, "count": 442 },
  { "id": 75, "name": "体温计", "region": "华南", "year": 2022, "count": 453 },
  { "id": 76, "name": "剃须刀", "region": "华东", "year": 2023, "count": 464 },
  { "id": 77, "name": "吹风机", "region": "华北", "year": 2024, "count": 475 },
  { "id": 78, "name": "卷发棒", "region": "华南", "year": 2023, "count": 486 },
  { "id": 79, "name": "洁面仪", "region": "华东", "year": 2022, "count": 497 },
  { "id": 80, "name": "电动牙刷", "region": "华北", "year": 2023, "count": 508 },
  { "id": 81, "name": "冲牙器", "region": "西南", "year": 2021, "count": 519 },
  { "id": 82, "name": "足浴盆", "region": "华东", "year": 2024, "count": 531 },
  { "id": 83, "name": "按摩披肩", "region": "华南", "year": 2023, "count": 542 },
  { "id": 84, "name": "护眼仪", "region": "华北", "year": 2022, "count": 553 },
  { "id": 85, "name": "颈椎仪", "region": "华东", "year": 2023, "count": 564 },
  { "id": 86, "name": "筋膜枪", "region": "华南", "year": 2024, "count": 575 },
  { "id": 87, "name": "智能枕头", "region": "华北", "year": 2023, "count": 586 },
  { "id": 88, "name": "智能被", "region": "华东", "year": 2022, "count": 597 },
  { "id": 89, "name": "智能床", "region": "西南", "year": 2023, "count": 608 },
  { "id": 90, "name": "智能沙发", "region": "华南", "year": 2021, "count": 619 },
  { "id": 91, "name": "智能茶几", "region": "华东", "year": 2024, "count": 631 },
  { "id": 92, "name": "智能镜子", "region": "华北", "year": 2023, "count": 642 },
  { "id": 93, "name": "智能马桶", "region": "华南", "year": 2022, "count": 653 },
  { "id": 94, "name": "智能浴缸", "region": "华东", "year": 2023, "count": 664 },
  { "id": 95, "name": "智能花洒", "region": "华北", "year": 2024, "count": 675 },
  { "id": 96, "name": "智能水龙头", "region": "西南", "year": 2023, "count": 686 },
  { "id": 97, "name": "智能橱柜", "region": "华东", "year": 2022, "count": 697 },
  { "id": 98, "name": "智能衣柜", "region": "华南", "year": 2023, "count": 708 },
  { "id": 99, "name": "智能鞋柜", "region": "华北", "year": 2021, "count": 719 },
  { "id": 100, "name": "智能晾衣架", "region": "华东", "year": 2024, "count": 731 }
]